fast_agent/__init__.py
fast_agent/config.py
fast_agent/constants.py
fast_agent/context.py
fast_agent/context_dependent.py
fast_agent/event_progress.py
fast_agent/interfaces.py
fast_agent/mcp_server_registry.py
fast_agent/paths.py
fast_agent/py.typed
fast_agent/workflow_telemetry.py
fast_agent/acp/__init__.py
fast_agent/acp/acp_aware_mixin.py
fast_agent/acp/acp_context.py
fast_agent/acp/command_io.py
fast_agent/acp/content_conversion.py
fast_agent/acp/filesystem_runtime.py
fast_agent/acp/permission_store.py
fast_agent/acp/protocols.py
fast_agent/acp/slash_commands.py
fast_agent/acp/terminal_runtime.py
fast_agent/acp/tool_permission_adapter.py
fast_agent/acp/tool_permissions.py
fast_agent/acp/tool_progress.py
fast_agent/acp/adapters/__init__.py
fast_agent/acp/adapters/acp_io.py
fast_agent/acp/server/__init__.py
fast_agent/acp/server/agent_acp_server.py
fast_agent/agents/__init__.py
fast_agent/agents/agent_types.py
fast_agent/agents/llm_agent.py
fast_agent/agents/llm_decorator.py
fast_agent/agents/mcp_agent.py
fast_agent/agents/smart_agent.py
fast_agent/agents/tool_agent.py
fast_agent/agents/tool_runner.py
fast_agent/agents/workflow/agents_as_tools_agent.py
fast_agent/agents/workflow/chain_agent.py
fast_agent/agents/workflow/evaluator_optimizer.py
fast_agent/agents/workflow/iterative_planner.py
fast_agent/agents/workflow/maker_agent.py
fast_agent/agents/workflow/orchestrator_models.py
fast_agent/agents/workflow/orchestrator_prompts.py
fast_agent/agents/workflow/parallel_agent.py
fast_agent/agents/workflow/router_agent.py
fast_agent/cli/__init__.py
fast_agent/cli/__main__.py
fast_agent/cli/asyncio_utils.py
fast_agent/cli/constants.py
fast_agent/cli/env_helpers.py
fast_agent/cli/main.py
fast_agent/cli/shared_options.py
fast_agent/cli/terminal.py
fast_agent/cli/commands/acp.py
fast_agent/cli/commands/auth.py
fast_agent/cli/commands/check_config.py
fast_agent/cli/commands/config.py
fast_agent/cli/commands/demo.py
fast_agent/cli/commands/go.py
fast_agent_mcp-0.4.46.dist-info/METADATA
fast_agent_mcp-0.4.46.dist-info/WHEEL
fast_agent_mcp-0.4.46.dist-info/entry_points.txt
fast_agent_mcp-0.4.46.dist-info/licenses/LICENSE
fast_agent_mcp-0.4.46.dist-info/licenses/NOTICE
fast_agent_mcp-0.4.46.dist-info/RECORD
