Metadata-Version: 2.4
Name: fast-agent-mcp
Version: 0.4.46
Summary: Define, Prompt and Test MCP enabled Agents and Workflows
Author-email: Shaun Smith <fastagent@llmindset.co.uk>
License:                                  Apache License
License-File: LICENSE
License-File: NOTICE
Classifier: License :: OSI Approved :: Apache Software License
Classifier: Operating System :: OS Independent
Classifier: Programming Language :: Python :: 3
Requires-Python: <3.14,>=3.13.5
Requires-Dist: a2a-sdk>=0.3.16
Requires-Dist: agent-client-protocol>=0.7.1
Requires-Dist: aiohttp>=3.13.2
Requires-Dist: anthropic>=0.76
Requires-Dist: deprecated>=1.2.18
Requires-Dist: email-validator>=2.2.0
Requires-Dist: fastapi>=0.121.0
Requires-Dist: google-genai>=1.52.0
Requires-Dist: keyring>=24.3.1
Requires-Dist: mcp==1.26.0
Requires-Dist: multilspy>=0.0.15
Requires-Dist: openai[aiohttp]>=2.15.0
Requires-Dist: opentelemetry-distro>=0.60b1
Requires-Dist: opentelemetry-exporter-otlp-proto-http>=1.7.0
Requires-Dist: opentelemetry-instrumentation-anthropic>=0.51.1; python_version >= '3.10' and python_version < '4.0'
Requires-Dist: opentelemetry-instrumentation-google-genai>=0.4b0
Requires-Dist: opentelemetry-instrumentation-mcp>=0.49.5; python_version >= '3.10' and python_version < '4.0'
Requires-Dist: opentelemetry-instrumentation-openai>=0.49.5; python_version >= '3.10' and python_version < '4.0'
Requires-Dist: prompt-toolkit>=3.0.52
Requires-Dist: pydantic-settings>=2.7.0
Requires-Dist: pydantic>=2.10.4
Requires-Dist: pyperclip>=1.9.0
Requires-Dist: python-frontmatter>=1.1.0
Requires-Dist: pyyaml>=6.0.2
Requires-Dist: rich>=14.3.1
Requires-Dist: ruamel-yaml>=0.18.16
Requires-Dist: tiktoken>=0.12.0
Requires-Dist: typer>=0.21.1
Requires-Dist: uvloop>=0.22.1; platform_system != 'Windows'
Requires-Dist: watchfiles>=1.1.0
Provides-Extra: all-providers
Requires-Dist: azure-identity>=1.14.0; extra == 'all-providers'
Requires-Dist: boto3>=1.35.0; extra == 'all-providers'
Requires-Dist: tensorzero>=2025.7.5; extra == 'all-providers'
Provides-Extra: azure
Requires-Dist: azure-identity>=1.14.0; extra == 'azure'
Provides-Extra: bedrock
Requires-Dist: boto3>=1.35.0; extra == 'bedrock'
Provides-Extra: tensorzero
Requires-Dist: tensorzero>=2025.7.5; extra == 'tensorzero'
Provides-Extra: textual
Requires-Dist: textual>=6.2.1; extra == 'textual'
